OSPO
