Metadata-Version: 1.0
Name: HMSFire
Version: 0.3.15
Summary: This is a proof of concept package for Hazard Mapping System Fire Analysis
Home-page: https://ospo-hms-fire.readthedocs.io/en/latest/
Author: Joel
Author-email: joel.chacon@cimat.mx
License: MIT
Keywords: HMSFirepy project
Platform: UNKNOWN
